mmcb/__init__.py
mmcb/common.py
mmcb/configure_environment.py
mmcb/dat2plot.py
mmcb/dat2plotsep.py
mmcb/dat2root.py
mmcb/detect.py
mmcb/dmm.py
mmcb/dmm_interface.py
mmcb/iv.py
mmcb/lexicon.py
mmcb/liveplot.py
mmcb/log2dat.py
mmcb/peltier.py
mmcb/psuset.py
mmcb/psustat.py
mmcb/psuwatch.py
mmcb/sense.py
mmcb/sensors.py
mmcb/sequence.py
mmcb/ult80.py
mmcb_avt-1.0.34.dist-info/licenses/LICENSE
mmcb_avt-1.0.34.dist-info/METADATA
mmcb_avt-1.0.34.dist-info/WHEEL
mmcb_avt-1.0.34.dist-info/entry_points.txt
mmcb_avt-1.0.34.dist-info/top_level.txt
mmcb_avt-1.0.34.dist-info/RECORD
