Metadata-Version: 2.4
Name: mmcb-avt
Version: 1.0.34
Summary: ATLAS ITK Pixels Multi-Module Cycling Box environmental monitoring/control
Home-page: https://gitlab.ph.liv.ac.uk/avt/atlas-itk-pmmcb
Author: Alan Taylor, Manex Ormazabal
Author-email: avt@hep.ph.liv.ac.uk
Maintainer: Alan Taylor
Maintainer-email: avt@hep.ph.liv.ac.uk
Classifier: Development Status :: 5 - Production/Stable
Classifier: Intended Audience :: Developers
Classifier: Intended Audience :: Science/Research
Classifier: Topic :: Scientific/Engineering :: Physics
Classifier: Environment :: Console
Classifier: Environment :: X11 Applications
Classifier: Programming Language :: Python :: 3
Classifier: Programming Language :: Python :: 3 :: Only
Classifier: Programming Language :: Python :: 3.6
Classifier: Programming Language :: Python :: 3.7
Classifier: Programming Language :: Python :: 3.8
Classifier: Programming Language :: Python :: 3.9
Classifier: Programming Language :: Python :: 3.10
Classifier: Programming Language :: Python :: 3.11
Classifier: Programming Language :: Python :: 3.12
Classifier: Programming Language :: Python :: 3.13
Classifier: Operating System :: POSIX :: Linux
Classifier: Natural Language :: English
Classifier: License :: OSI Approved :: European Union Public Licence 1.2 (EUPL 1.2)
Requires-Python: >=3.6
License-File: LICENSE
Requires-Dist: numpy
Requires-Dist: pandas
Requires-Dist: matplotlib
Requires-Dist: zmq
Requires-Dist: pyserial==3.4.*
Requires-Dist: smbus
Requires-Dist: tables
Requires-Dist: RPi.GPIO
Requires-Dist: Adafruit-Blinka
Requires-Dist: adafruit-circuitpython-ads1x15
Requires-Dist: adafruit-circuitpython-bme680
Requires-Dist: adafruit-circuitpython-pcf8591
Requires-Dist: adafruit-circuitpython-sht4x
Requires-Dist: adafruit-circuitpython-shtc3
Requires-Dist: sparkfun-qwiic-tca9548a
Requires-Dist: yoctopuce
Dynamic: author
Dynamic: author-email
Dynamic: classifier
Dynamic: description
Dynamic: description-content-type
Dynamic: home-page
Dynamic: license-file
Dynamic: maintainer
Dynamic: maintainer-email
Dynamic: requires-dist
Dynamic: requires-python
Dynamic: summary
